raipred/Data/AAIndexNames.csv
raipred/Data/Grantham.csv
raipred/Data/PhysicoChemical.csv
raipred/Data/Schneider-Wrede.csv
raipred/Data/aa_attr_group.csv
raipred/Data/aaind.txt
raipred/Data/aaindex.csv
raipred/Data/aaindices.csv
raipred/Data/atom.csv
raipred/Data/bin_di.csv
raipred/Data/bonds.csv
raipred/Data/can_pat.csv
raipred/Data/z_aaindex.csv
raipred/Model/MERCI_motif_locator.pl
raipred/Model/envfile
raipred/Model/xgb_model_server
raipred/Python_scripts/__init__.py
raipred/Python_scripts/raipred.py
raipred/motifs/pos_motif.txt
raipred-1.1.dist-info/METADATA
raipred-1.1.dist-info/WHEEL
raipred-1.1.dist-info/entry_points.txt
raipred-1.1.dist-info/top_level.txt
raipred-1.1.dist-info/RECORD
