Metadata-Version: 2.1
Name: raipred
Version: 1.1
Summary: A tool to predict rheumatoid arthritis inducing peptides
Home-page: https://github.com/raghavagps/raipred
Requires-Python: >=3.6
Requires-Dist: pandas
Requires-Dist: xgboost==1.3.3
Requires-Dist: scikit-learn==1.0.1
